zerozen/__init__.py
zerozen/agents.py
zerozen/chat.py
zerozen/cli.py
zerozen/output_text_formatter.py
zerozen/proxy.py
zerozen/utils.py
zerozen/agenthub/__init__.py
zerozen/agenthub/main.py
zerozen/agenthub/memagent.py
zerozen/agenthub/web_search.py
zerozen/integrations/__init__.py
zerozen/integrations/google/__init__.py
zerozen/integrations/google/calendar_tool.py
zerozen/integrations/google/creds.py
zerozen/integrations/google/gmail_tool.py
zerozen/integrations/google/google_agent.py
zerozen/integrations/google/main.py
zerozen/memory/api.py
zerozen/memory/embedding.py
zerozen/memory/tools.py
zerozen-2025.9.20.dist-info/METADATA
zerozen-2025.9.20.dist-info/WHEEL
zerozen-2025.9.20.dist-info/entry_points.txt
zerozen-2025.9.20.dist-info/licenses/LICENSE
zerozen-2025.9.20.dist-info/RECORD
