Metadata-Version: 2.4
Name: zerozen
Version: 2025.9.20
Summary: hyper-personal, always-on, open-source AI companion.
License-File: LICENSE
Requires-Python: >=3.10
Requires-Dist: backoff>=2.2.1
Requires-Dist: fastmcp>=2.7.1
Requires-Dist: google-api-core>=2.25.1
Requires-Dist: google-api-python-client>=2.178.0
Requires-Dist: google-auth-httplib2>=0.2.0
Requires-Dist: google-auth-oauthlib>=1.2.2
Requires-Dist: google-auth>=2.40.3
Requires-Dist: googleapis-common-protos>=1.70.0
Requires-Dist: lancedb>=0.25.0
Requires-Dist: openai-agents>=0.2.2
Requires-Dist: openai>=1.97.0
Requires-Dist: pandas>=2.3.2
Requires-Dist: python-dotenv>=1.0.0
Requires-Dist: rich>=14.0.0
Requires-Dist: sentence-transformers>=5.1.0
Requires-Dist: typeguard>=4.4.4
Requires-Dist: typer>=0.16.0
